{
  "project_info": {
    "project_number": "50719577631",
    "project_id": "insatgram-clone-7f9f0",
    "storage_bucket": "insatgram-clone-7f9f0.appspot.com"
  },
  "client": [
    {
      "client_info": {
        "mobilesdk_app_id": "1:50719577631:android:c2c3ad6497417d6443a72a",
        "android_client_info": {
          "package_name": "com.example.instagram"
        }
      },
      "oauth_client": [
        {
          "client_id": "50719577631-mu592g12u3t7tdqrh9fbnrornpbsb66o.apps.googleusercontent.com",
          "client_type": 3
        }
      ],
      "api_key": [
        {
          "current_key": "AIzaSyAuSrNyFdbw3o4IsJtmayfa-ol2Ty4UCrs"
        }
      ],
      "services": {
        "appinvite_service": {
          "other_platform_oauth_client": [
            {
              "client_id": "50719577631-mu592g12u3t7tdqrh9fbnrornpbsb66o.apps.googleusercontent.com",
              "client_type": 3
            }
          ]
        }
      }
    }
  ],
  "configuration_version": "1"
}